AVMYT/__init__.py
AVMYT-0.1.0.dist-info/LICENSE
AVMYT-0.1.0.dist-info/METADATA
AVMYT-0.1.0.dist-info/WHEEL
AVMYT-0.1.0.dist-info/top_level.txt
AVMYT-0.1.0.dist-info/RECORD
