Metadata-Version: 2.1
Name: AVMYT
Version: 0.1.0
Summary: Get information from Youtube in a simple way.
Home-page: https://github.com/avmmodules/AVMYT
Author: AlejandroV
Author-email: avmmodules@gmail.com
License: UNKNOWN
Project-URL: Bug Tracker, https://github.com/avmmodules/AVMYT/issues
Platform: UNKNOWN
Classifier: Programming Language :: Python :: 3
Classifier: License :: OSI Approved :: MIT License
Classifier: Operating System :: OS Independent
Requires-Python: >=3.6
License-File: LICENSE
